LICENSE
README.md
setup.py
pyTirs/__init__.py
pyTirs.egg-info/PKG-INFO
pyTirs.egg-info/SOURCES.txt
pyTirs.egg-info/dependency_links.txt
pyTirs.egg-info/entry_points.txt
pyTirs.egg-info/requires.txt
pyTirs.egg-info/top_level.txt