Metadata-Version: 2.1
Name: pyTirs
Version: 0.0.1
Summary: Package Python perkuliahan yang diampu Tirta Setiawan di Prodi Sains Data Fakultas Sains Institut Teknologi Sumatera
Home-page: https://github.com/setiawantirta/pyTirs
Author: tirta setiawan
Author-email: tirta.setiawan@sd.itera.ac.id
License: BSD 2-clause
Platform: UNKNOWN
Classifier: Development Status :: 1 - Planning
Classifier: Intended Audience :: Science/Research
Classifier: License :: OSI Approved :: MIT License
Classifier: Operating System :: OS Independent
Classifier: Programming Language :: Python :: 3
License-File: LICENSE
